homebrew_pypi_poet-0.10.0.dist-info/DESCRIPTION.rst
homebrew_pypi_poet-0.10.0.dist-info/METADATA
homebrew_pypi_poet-0.10.0.dist-info/RECORD
homebrew_pypi_poet-0.10.0.dist-info/WHEEL
homebrew_pypi_poet-0.10.0.dist-info/entry_points.txt
homebrew_pypi_poet-0.10.0.dist-info/metadata.json
homebrew_pypi_poet-0.10.0.dist-info/top_level.txt
poet/__init__.py
poet/__main__.py
poet/lint.py
poet/poet.py
poet/templates.py
poet/util.py
poet/version.py
