Metadata-Version: 1.1
Name: homebrew-pypi-poet
Version: 0.10.0
Summary: Writes Homebrew stanzas for pypi packages
Home-page: https://github.com/tdsmith/homebrew-pypi-poet
Author: Tim D. Smith
Author-email: poet@tim-smith.us
License: MIT
Platform: any
Classifier: Development Status :: 4 - Beta
Classifier: Intended Audience :: Developers
Classifier: Topic :: Software Development :: Build Tools
Classifier: License :: OSI Approved :: MIT License
Classifier: Programming Language :: Python :: 2.7
Classifier: Programming Language :: Python :: 3.6
